requirements.txt
PyRuSH/PyRuSHSentencizer.py
PyRuSH/RuSH.py
PyRuSH/StaticSentencizerFun.cpp
PyRuSH/StaticSentencizerFun.cpython-39-x86_64-linux-gnu.so
PyRuSH/StaticSentencizerFun.pyx
PyRuSH/__init__.py
conf/rush_rules.tsv
pyrush-1.0.12.dist-info/METADATA
pyrush-1.0.12.dist-info/WHEEL
pyrush-1.0.12.dist-info/top_level.txt
pyrush-1.0.12.dist-info/RECORD
pyrush-1.0.12.dist-info/licenses/LICENSE
