Metadata-Version: 2.4
Name: PyRuSH
Version: 1.0.12
Summary: PyRuSH is the python implementation of RuSH (Rule-based sentence Segmenter using Hashing), which is originally developed using Java. RuSH is an efficient, reliable, and easy adaptable rule-based sentence segmentation solution. It is specifically designed to handle the telegraphic written text in clinical note. It leverages a nested hash table to execute simultaneous rule processing, which reduces the impact of the rule-base growth on execution time and eliminates the effect of rule orde
Home-page: https://github.com/jianlins/PyRuSH
Author: Jianlin
Author-email: Jianlin <jianlinshi.cn@gmail.com>
License-Expression: MIT
Project-URL: Source, https://github.com/jianlins/PyRuSH
Keywords: PyRuSH,NLP,sentenczier,sentence segmentation
Classifier: Programming Language :: Python :: 3
Requires-Python: >=3.6
License-File: LICENSE
Requires-Dist: Cython
Requires-Dist: setuptools
Requires-Dist: spacy<3.8; python_version < "3.12"
Requires-Dist: spacy>=3.8; python_version >= "3.12"
Requires-Dist: PyFastNER>=1.0.8
Requires-Dist: quicksectx>=0.3.5
Requires-Dist: loguru
Dynamic: author
Dynamic: home-page
Dynamic: license-file
